{
"type": "FeatureCollection",
"name": "waypoints",
"crs": { "type": "name", "properties": { "name": "urn:ogc:def:crs:OGC:1.3:CRS84" } },
"features": [
{ "type": "Feature", "properties": { "name": "Launchpad" }, "geometry": { "type": "Point", "coordinates": [ -71.25863, 42.29126 ] } }
]
}
